LICENSE.txt
MANIFEST.in
README.md
setup.cfg
setup.py
nucosObs/__init__.py
nucosObs/aiohttpWebsocketInterface.py
nucosObs/observable.py
nucosObs/observer.py
nucosObs/stdinInterface.py
nucosObs/twoWayInterface.py
nucosObs/version.py
nucosObs/websocketInterface.py
nucosObs.egg-info/PKG-INFO
nucosObs.egg-info/SOURCES.txt
nucosObs.egg-info/dependency_links.txt
nucosObs.egg-info/requires.txt
nucosObs.egg-info/top_level.txt