Metadata-Version: 2.1
Name: nucosObs
Version: 0.4.17
Summary: nucosObs - an observer/observable toolbox based on asyncio
Home-page: https://github.com/DocBO/nucosObs
Download-URL: https://github.com/DocBO/nucosObs/tarball/0.0.1
Author: Oliver Braun
Author-email: oliver.braun@nucos.de
License: MIT
Keywords: observer observable asyncio
Classifier: Development Status :: 1 - Planning
Classifier: Environment :: Console
Classifier: License :: OSI Approved :: MIT License
Classifier: Natural Language :: English
Classifier: Operating System :: OS Independent
Classifier: Programming Language :: Python :: 3.8
Classifier: Programming Language :: Python :: 3.9
Classifier: Programming Language :: Python :: 3.10
Classifier: Programming Language :: Python :: 3.11
License-File: LICENSE.txt
Requires-Dist: websockets
